{
  "featured": [
    {
      "id": "https://vnexpress.net/tuong-quan-tran-khai-mac-world-cup-2026-5084393.html",
      "category_id": "featured",
      "category_name": "Tin nổi bật",
      "source": "VnExpress",
      "title": "Tương quan trận khai mạc World Cup 2026",
      "description": "Trên sân đấu Azteca huyền thoại, chủ nhà Mexico hướng đến chiến thắng trước Nam Phi, trong ngày khai mạc World Cup 2026.",
      "thumbnail_url": "https://vcdn1-thethao.vnecdn.net/2026/06/11/r1669698x729-1781145058.jpg?w=1200&h=0&q=100&dpr=1&fit=crop&s=LU8UXFhPRSIjrbvOSKhdSA",
      "link": "https://vnexpress.net/tuong-quan-tran-khai-mac-world-cup-2026-5084393.html",
      "published_at": "Thu, 11 Jun 2026 17:15:45 +0700",
      "createAt": "2026-06-11T10:15:45.000Z"
    },
    {
      "id": "https://vnexpress.net/pho-tong-thong-my-ong-netanyahu-da-mac-mot-so-sai-lam-5084646.html",
      "category_id": "featured",
      "category_name": "Tin nổi bật",
      "source": "VnExpress",
      "title": "Phó tổng thống Mỹ: Ông Netanyahu đã mắc một số sai lầm",
      "description": "Phó tổng thống Vance đề cao quan hệ Mỹ - Israel, nhưng cho rằng Thủ tướng Netanyahu đã mắc sai lầm nhất định trong vấn đề liên quan đến Iran.",
      "thumbnail_url": "https://vcdn1-vnexpress.vnecdn.net/2026/06/11/ap26148802455680-1781172047-8405-1781172131.jpg?w=1200&h=0&q=100&dpr=1&fit=crop&s=5YCJOLgxT8Y7a42UomW7JQ",
      "link": "https://vnexpress.net/pho-tong-thong-my-ong-netanyahu-da-mac-mot-so-sai-lam-5084646.html",
      "published_at": "Thu, 11 Jun 2026 17:37:21 +0700",
      "createAt": "2026-06-11T10:37:21.000Z"
    },
    {
      "id": "https://vnexpress.net/lap-4-spa-thue-nhieu-nguoi-gia-bac-si-ve-benh-cho-khach-5084679.html",
      "category_id": "featured",
      "category_name": "Tin nổi bật",
      "source": "VnExpress",
      "title": "Lập 4 spa, thuê nhiều người giả bác sĩ 'vẽ bệnh' cho khách",
      "description": "Người học hết lớp 9, làm nghề shipper vẫn giả bác sĩ, cắt tạo hình thẩm mỹ phụ khoa và điều trị cho khách trong đường dây spa vừa bị triệt phá.",
      "thumbnail_url": "https://vcdn1-vnexpress.vnecdn.net/2026/06/11/1-1781174226-6894-1781174270.jpg?w=1200&h=0&q=100&dpr=1&fit=crop&s=3BUN5vWjxwVaiFAozMLZ5g",
      "link": "https://vnexpress.net/lap-4-spa-thue-nhieu-nguoi-gia-bac-si-ve-benh-cho-khach-5084679.html",
      "published_at": "Thu, 11 Jun 2026 17:52:23 +0700",
      "createAt": "2026-06-11T10:52:23.000Z"
    },
    {
      "id": "https://vnexpress.net/27-thi-sinh-bi-dinh-chi-thi-tot-nghiep-thpt-2026-trong-ngay-thi-dau-tien-5084689.html",
      "category_id": "featured",
      "category_name": "Tin nổi bật",
      "source": "VnExpress",
      "title": "11 thí sinh dùng điện thoại, tài liệu khi thi Toán tốt nghiệp THPT",
      "description": "27 thí sinh bị đình chỉ trong ngày thi tốt nghiệp THPT đầu tiên, nhiều hơn so với năm ngoái, riêng môn Toán là 11, chủ yếu do sử dụng điện thoại.",
      "thumbnail_url": "https://vcdn1-vnexpress.vnecdn.net/2026/06/11/2aoboqcgmbtbyn1rvhzjq1lhjplxcg-4246-7796-1781175504.jpg?w=1200&h=0&q=100&dpr=1&fit=crop&s=Kd7yO_Fx8bKD19tkswtWug",
      "link": "https://vnexpress.net/27-thi-sinh-bi-dinh-chi-thi-tot-nghiep-thpt-2026-trong-ngay-thi-dau-tien-5084689.html",
      "published_at": "Thu, 11 Jun 2026 18:04:18 +0700",
      "createAt": "2026-06-11T11:04:18.000Z"
    },
    {
      "id": "https://vnexpress.net/giao-vien-noi-de-toan-thi-tot-nghiep-thpt-2026-khong-he-de-tho-5084500.html",
      "category_id": "featured",
      "category_name": "Tin nổi bật",
      "source": "VnExpress",
      "title": "Dự đoán điểm trung bình Toán tăng, nhưng khó 'chạm' điểm 9, 10",
      "description": "Nhiều giáo viên cho rằng đề Toán thi tốt nghiệp THPT 2026 không giảm độ khó, do không còn bất ngờ nên thí sinh đạt điểm trên 5 tăng nhưng điểm 9, 10 sẽ giảm.",
      "thumbnail_url": "https://vcdn1-vnexpress.vnecdn.net/2026/06/11/z7925105676505-eb2a58b1492ee9b-5055-4553-1781175591.jpg?w=1200&h=0&q=100&dpr=1&fit=crop&s=rgpX-iFwNujwyNcuO_p7ow",
      "link": "https://vnexpress.net/giao-vien-noi-de-toan-thi-tot-nghiep-thpt-2026-khong-he-de-tho-5084500.html",
      "published_at": "Thu, 11 Jun 2026 18:17:00 +0700",
      "createAt": "2026-06-11T11:17:00.000Z"
    }
  ]
}