{
  "total_articles": 482,
  "files": [
    "chunk_1.json",
    "chunk_2.json",
    "chunk_3.json",
    "chunk_4.json",
    "chunk_5.json"
  ],
  "channel": {
    "title": "Xe - VnExpress RSS",
    "description": "VnExpress RSS",
    "generator": "VnExpress",
    "copyright": "",
    "logo_url": "https://s.vnecdn.net/vnexpress/i/v20/logos/vne_logo_rss.png",
    "link": "https://vnexpress.net/rss/oto-xe-may.rss",
    "last_updated": "Thu, 09 Jul 2026 06:01:46 +0700"
  },
  "last_updated": "2026-07-08T23:51:15.533Z"
}